{
  "schemaVersion": 2,
  "generatedFromPublicDataOnly": true,
  "release": {
    "id": "2026-07-23-decision-cockpit-audit-trail-v16",
    "version": "2026.07.23-16",
    "publishedAt": "2026-07-23T22:01:19+03:00"
  },
  "asOf": "2026-07-22",
  "languages": [
    "en",
    "fi"
  ],
  "publicBoundary": {
    "en": "Independent public evidence summary. Not Pixan Oy's official position; not an audit, valuation, legal opinion, investment recommendation or lending recommendation.",
    "fi": "Riippumaton julkinen evidenssikooste. Ei Pixan Oy:n virallinen kanta; ei tilintarkastus, arvonmääritys, oikeudellinen lausunto, sijoitussuositus tai lainasuositus."
  },
  "inputs": [
    {
      "path": "site/data/atlas.json",
      "sha256": "0a0d2e80106ceaef8a157bffdc8840dacb02080049a40a6428c239fae5c24dab"
    },
    {
      "path": "site/data/market-values.json",
      "sha256": "cdb7105ae69f524df86cddc6001c074d82d379a92dfbb69735e1f6fd4d1e6e46"
    },
    {
      "path": "site/data/patent-history.json",
      "sha256": "6c7851943384b633f6458953e0e21e1d4eb808aaaa67c86ed856c69a8aa746ef"
    },
    {
      "path": "site/data/changelog.json",
      "sha256": "475635556fb041581538f72e7a74c5e9fb9551c9020894c1505ecff286d8bd13"
    },
    {
      "path": "source/bank-evidence-register-en.json",
      "sha256": "494b217097563247044de2be3e43816e756f94f276bd69826a657f8f468ea246"
    },
    {
      "path": "source/bank-deck-en-translations.json",
      "sha256": "e7bab7fb36659186278ef8728449128b897482c5561475343a42d5cfbccc380d"
    },
    {
      "path": "source/bank-package-en-lock.json",
      "sha256": "a36f6775034a59ade3d7df11c9cb62cdebef1b0341fe96ef02f438311bcec9c0"
    }
  ],
  "artifacts": [
    {
      "id": "short-deck-en",
      "kind": "pptx",
      "language": "en",
      "titleFi": "Suppea pankkidekki (englanti)",
      "titleEn": "Concise bank deck (English)",
      "fileName": "pixan-bank-deck-short-en.pptx",
      "path": "downloads/pixan-bank-deck-short-en.pptx",
      "sha256": "ff07df15e3e857533b9e7110129f56fe610299639b56a542e07a388202d0732c",
      "bytes": 50627,
      "slideCount": 6
    },
    {
      "id": "medium-deck-en",
      "kind": "pptx",
      "language": "en",
      "titleFi": "Keskikokoinen pankkidekki (englanti)",
      "titleEn": "Core bank deck (English)",
      "fileName": "pixan-bank-deck-medium-en.pptx",
      "path": "downloads/pixan-bank-deck-medium-en.pptx",
      "sha256": "92a191d21cfc69a293342fcfbb60bc64a8eb546d4d0529fcc27dbb33cbb7c918",
      "bytes": 73278,
      "slideCount": 12
    },
    {
      "id": "large-deck-en",
      "kind": "pptx",
      "language": "en",
      "titleFi": "Laaja pankkidekki (englanti)",
      "titleEn": "Extended bank deck (English)",
      "fileName": "pixan-bank-deck-large-en.pptx",
      "path": "downloads/pixan-bank-deck-large-en.pptx",
      "sha256": "e518aa7fde0967f169fd61cb8b9b665d3d8b5e387710dc5b6af0a36a8ca8a03e",
      "bytes": 139874,
      "slideCount": 30
    },
    {
      "id": "evidence-register-en",
      "kind": "xlsx",
      "language": "en",
      "titleFi": "Evidence Register (englanti)",
      "titleEn": "Evidence Register (English)",
      "fileName": "pixan-bank-evidence-register-en.xlsx",
      "path": "downloads/pixan-bank-evidence-register-en.xlsx",
      "sha256": "317141d886dbfc7ebaeeb9ba5f6bfdcf2df1efb2e453c64fd2e838a594074ce6",
      "bytes": 23735,
      "rowCount": 45
    },
    {
      "id": "short-deck-fi",
      "kind": "pptx",
      "language": "fi",
      "titleFi": "Suppea pankkidekki (suomi)",
      "titleEn": "Concise bank deck (Finnish)",
      "fileName": "pixan-bank-deck-short-fi.pptx",
      "path": "downloads/pixan-bank-deck-short-fi.pptx",
      "sha256": "cf92f924f8636b4c2e84de130e8e96cb29bfc1f7fcbc61741aaa472f2f0277ac",
      "bytes": 161042,
      "slideCount": 6
    },
    {
      "id": "medium-deck-fi",
      "kind": "pptx",
      "language": "fi",
      "titleFi": "Keskikokoinen pankkidekki (suomi)",
      "titleEn": "Core bank deck (Finnish)",
      "fileName": "pixan-bank-deck-medium-fi.pptx",
      "path": "downloads/pixan-bank-deck-medium-fi.pptx",
      "sha256": "84fd0c4765f8cb4b5d985e3f4a33f4d60d727621a57dc86be96328b5cac44f3e",
      "bytes": 234558,
      "slideCount": 12
    },
    {
      "id": "large-deck-fi",
      "kind": "pptx",
      "language": "fi",
      "titleFi": "Laaja pankkidekki (suomi)",
      "titleEn": "Extended bank deck (Finnish)",
      "fileName": "pixan-bank-deck-large-fi.pptx",
      "path": "downloads/pixan-bank-deck-large-fi.pptx",
      "sha256": "858bd3f09d42ca2ccc454e8b0ac93ae874759d56e790e111324ce65f2f652609",
      "bytes": 467496,
      "slideCount": 30
    },
    {
      "id": "evidence-register-fi",
      "kind": "xlsx",
      "language": "fi",
      "titleFi": "Evidence Register (suomi)",
      "titleEn": "Evidence Register (Finnish)",
      "fileName": "pixan-bank-evidence-register-fi.xlsx",
      "path": "downloads/pixan-bank-evidence-register-fi.xlsx",
      "sha256": "a1bf5b5014e5d0ed22d985b78452c39123c597a8c9db3269e370399bb5fd6b63",
      "bytes": 103396,
      "rowCount": 45
    }
  ]
}
